{".class":"MypyFile","_fullname":"FastVideo.fastvideo.configs.models.dits.base","future_import_flags":[],"is_partial_stub_package":false,"is_stub":false,"names":{".class":"SymbolTable","Any":{".class":"SymbolTableNode","cross_ref":"typing.Any","kind":"Gdef"},"ArchConfig":{".class":"SymbolTableNode","kind":"Gdef","node":{".class":"Var","flags":["is_suppressed_import","is_ready","is_inferred"],"fullname":"FastVideo.fastvideo.configs.models.dits.base.ArchConfig","name":"ArchConfig","type":{".class":"AnyType","missing_import_name":"FastVideo.fastvideo.configs.models.dits.base.ArchConfig","source_any":null,"type_of_any":3}}},"AttentionBackendEnum":{".class":"SymbolTableNode","kind":"Gdef","node":{".class":"Var","flags":["is_suppressed_import","is_ready","is_inferred"],"fullname":"FastVideo.fastvideo.configs.models.dits.base.AttentionBackendEnum","name":"AttentionBackendEnum","type":{".class":"AnyType","missing_import_name":"FastVideo.fastvideo.configs.models.dits.base.AttentionBackendEnum","source_any":null,"type_of_any":3}}},"DiTArchConfig":{".class":"SymbolTableNode","kind":"Gdef","node":{".class":"TypeInfo","_promote":[],"abstract_attributes":[],"alt_promote":null,"bases":["builtins.object"],"dataclass_transform_spec":null,"declared_metaclass":null,"defn":{".class":"ClassDef","fullname":"FastVideo.fastvideo.configs.models.dits.base.DiTArchConfig","name":"DiTArchConfig","type_vars":[]},"deletable_attributes":[],"deprecated":null,"flags":["fallback_to_any"],"fullname":"FastVideo.fastvideo.configs.models.dits.base.DiTArchConfig","has_param_spec_type":false,"metaclass_type":null,"metadata":{"dataclass":{"attributes":[{"alias":null,"column":4,"has_default":true,"is_in_init":true,"is_init_var":false,"is_neither_frozen_nor_nonfrozen":false,"kw_only":false,"line":12,"name":"_fsdp_shard_conditions","type":{".class":"Instance","args":[{".class":"AnyType","missing_import_name":null,"source_any":null,"type_of_any":4}],"extra_attrs":null,"type_ref":"builtins.list"}},{"alias":null,"column":4,"has_default":true,"is_in_init":true,"is_init_var":false,"is_neither_frozen_nor_nonfrozen":false,"kw_only":false,"line":13,"name":"_compile_conditions","type":{".class":"Instance","args":[{".class":"AnyType","missing_import_name":null,"source_any":null,"type_of_any":4}],"extra_attrs":null,"type_ref":"builtins.list"}},{"alias":null,"column":4,"has_default":true,"is_in_init":true,"is_init_var":false,"is_neither_frozen_nor_nonfrozen":false,"kw_only":false,"line":14,"name":"param_names_mapping","type":{".class":"Instance","args":[{".class":"AnyType","missing_import_name":null,"source_any":null,"type_of_any":4},{".class":"AnyType","missing_import_name":null,"source_any":null,"type_of_any":4}],"extra_attrs":null,"type_ref":"builtins.dict"}},{"alias":null,"column":4,"has_default":true,"is_in_init":true,"is_init_var":false,"is_neither_frozen_nor_nonfrozen":false,"kw_only":false,"line":15,"name":"reverse_param_names_mapping","type":{".class":"Instance","args":[{".class":"AnyType","missing_import_name":null,"source_any":null,"type_of_any":4},{".class":"AnyType","missing_import_name":null,"source_any":null,"type_of_any":4}],"extra_attrs":null,"type_ref":"builtins.dict"}},{"alias":null,"column":4,"has_default":true,"is_in_init":true,"is_init_var":false,"is_neither_frozen_nor_nonfrozen":false,"kw_only":false,"line":16,"name":"lora_param_names_mapping","type":{".class":"Instance","args":[{".class":"AnyType","missing_import_name":null,"source_any":null,"type_of_any":4},{".class":"AnyType","missing_import_name":null,"source_any":null,"type_of_any":4}],"extra_attrs":null,"type_ref":"builtins.dict"}},{"alias":null,"column":4,"has_default":true,"is_in_init":true,"is_init_var":false,"is_neither_frozen_nor_nonfrozen":false,"kw_only":false,"line":17,"name":"_supported_attention_backends","type":{".class":"Instance","args":[{".class":"AnyType","missing_import_name":"FastVideo.fastvideo.configs.models.dits.base.AttentionBackendEnum","source_any":null,"type_of_any":3}],"extra_attrs":null,"type_ref":"builtins.tuple"}},{"alias":null,"column":4,"has_default":true,"is_in_init":true,"is_init_var":false,"is_neither_frozen_nor_nonfrozen":false,"kw_only":false,"line":23,"name":"hidden_size","type":"builtins.int"},{"alias":null,"column":4,"has_default":true,"is_in_init":true,"is_init_var":false,"is_neither_frozen_nor_nonfrozen":false,"kw_only":false,"line":24,"name":"num_attention_heads","type":"builtins.int"},{"alias":null,"column":4,"has_default":true,"is_in_init":true,"is_init_var":false,"is_neither_frozen_nor_nonfrozen":false,"kw_only":false,"line":25,"name":"num_channels_latents","type":"builtins.int"},{"alias":null,"column":4,"has_default":true,"is_in_init":true,"is_init_var":false,"is_neither_frozen_nor_nonfrozen":false,"kw_only":false,"line":26,"name":"in_channels","type":"builtins.int"},{"alias":null,"column":4,"has_default":true,"is_in_init":true,"is_init_var":false,"is_neither_frozen_nor_nonfrozen":false,"kw_only":false,"line":27,"name":"out_channels","type":"builtins.int"},{"alias":null,"column":4,"has_default":true,"is_in_init":true,"is_init_var":false,"is_neither_frozen_nor_nonfrozen":false,"kw_only":false,"line":28,"name":"exclude_lora_layers","type":{".class":"Instance","args":["builtins.str"],"extra_attrs":null,"type_ref":"builtins.list"}},{"alias":null,"column":4,"has_default":true,"is_in_init":true,"is_init_var":false,"is_neither_frozen_nor_nonfrozen":false,"kw_only":false,"line":29,"name":"boundary_ratio","type":{".class":"UnionType","items":["builtins.float",{".class":"NoneType"}],"uses_pep604_syntax":true}}],"frozen":false},"dataclass_tag":{}},"module_name":"FastVideo.fastvideo.configs.models.dits.base","mro":["FastVideo.fastvideo.configs.models.dits.base.DiTArchConfig","builtins.object"],"names":{".class":"SymbolTable","__dataclass_fields__":{".class":"SymbolTableNode","kind":"Mdef","node":{".class":"Var","flags":["is_classvar","is_ready"],"fullname":"FastVideo.fastvideo.configs.models.dits.base.DiTArchConfig.__dataclass_fields__","name":"__dataclass_fields__","type":{".class":"Instance","args":["builtins.str",{".class":"Instance","args":[{".class":"AnyType","missing_import_name":null,"source_any":null,"type_of_any":2}],"extra_attrs":null,"type_ref":"dataclasses.Field"}],"extra_attrs":null,"type_ref":"builtins.dict"}},"plugin_generated":true},"__init__":{".class":"SymbolTableNode","kind":"Mdef","node":{".class":"FuncDef","abstract_status":0,"arg_kinds":[0,2,1,1,1,1,1,1,1,1,1,1,1,1,1,4],"arg_names":["self","generated_args","_fsdp_shard_conditions","_compile_conditions","param_names_mapping","reverse_param_names_mapping","lora_param_names_mapping","_supported_attention_backends","hidden_size","num_attention_heads","num_channels_latents","in_channels","out_channels","exclude_lora_layers","boundary_ratio","generated_kwargs"],"dataclass_transform_spec":null,"deprecated":null,"flags":[],"fullname":"FastVideo.fastvideo.configs.models.dits.base.DiTArchConfig.__init__","name":"__init__","type":{".class":"CallableType","arg_kinds":[0,2,1,1,1,1,1,1,1,1,1,1,1,1,1,4],"arg_names":["self","generated_args","_fsdp_shard_conditions","_compile_conditions","param_names_mapping","reverse_param_names_mapping","lora_param_names_mapping","_supported_attention_backends","hidden_size","num_attention_heads","num_channels_latents","in_channels","out_channels","exclude_lora_layers","boundary_ratio","generated_kwargs"],"arg_types":["FastVideo.fastvideo.configs.models.dits.base.DiTArchConfig",{".class":"AnyType","missing_import_name":null,"source_any":null,"type_of_any":2},{".class":"Instance","args":[{".class":"AnyType","missing_import_name":null,"source_any":null,"type_of_any":4}],"extra_attrs":null,"type_ref":"builtins.list"},{".class":"Instance","args":[{".class":"AnyType","missing_import_name":null,"source_any":null,"type_of_any":4}],"extra_attrs":null,"type_ref":"builtins.list"},{".class":"Instance","args":[{".class":"AnyType","missing_import_name":null,"source_any":null,"type_of_any":4},{".class":"AnyType","missing_import_name":null,"source_any":null,"type_of_any":4}],"extra_attrs":null,"type_ref":"builtins.dict"},{".class":"Instance","args":[{".class":"AnyType","missing_import_name":null,"source_any":null,"type_of_any":4},{".class":"AnyType","missing_import_name":null,"source_any":null,"type_of_any":4}],"extra_attrs":null,"type_ref":"builtins.dict"},{".class":"Instance","args":[{".class":"AnyType","missing_import_name":null,"source_any":null,"type_of_any":4},{".class":"AnyType","missing_import_name":null,"source_any":null,"type_of_any":4}],"extra_attrs":null,"type_ref":"builtins.dict"},{".class":"Instance","args":[{".class":"AnyType","missing_import_name":"FastVideo.fastvideo.configs.models.dits.base.AttentionBackendEnum","source_any":null,"type_of_any":3}],"extra_attrs":null,"type_ref":"builtins.tuple"},"builtins.int","builtins.int","builtins.int","builtins.int","builtins.int",{".class":"Instance","args":["builtins.str"],"extra_attrs":null,"type_ref":"builtins.list"},{".class":"UnionType","items":["builtins.float",{".class":"NoneType"}],"uses_pep604_syntax":false},{".class":"AnyType","missing_import_name":null,"source_any":null,"type_of_any":2}],"bound_args":[],"def_extras":{},"fallback":"builtins.function","from_concatenate":false,"implicit":false,"imprecise_arg_kinds":false,"is_ellipsis_args":false,"name":"__init__ of DiTArchConfig","ret_type":{".class":"NoneType"},"type_guard":null,"type_is":null,"unpack_kwargs":false,"variables":[]}},"plugin_generated":true},"__match_args__":{".class":"SymbolTableNode","kind":"Mdef","node":{".class":"Var","flags":["is_ready","allow_incompatible_override"],"fullname":"FastVideo.fastvideo.configs.models.dits.base.DiTArchConfig.__match_args__","name":"__match_args__","type":{".class":"TupleType","implicit":false,"items":[{".class":"LiteralType","fallback":"builtins.str","value":"_fsdp_shard_conditions"},{".class":"LiteralType","fallback":"builtins.str","value":"_compile_conditions"},{".class":"LiteralType","fallback":"builtins.str","value":"param_names_mapping"},{".class":"LiteralType","fallback":"builtins.str","value":"reverse_param_names_mapping"},{".class":"LiteralType","fallback":"builtins.str","value":"lora_param_names_mapping"},{".class":"LiteralType","fallback":"builtins.str","value":"_supported_attention_backends"},{".class":"LiteralType","fallback":"builtins.str","value":"hidden_size"},{".class":"LiteralType","fallback":"builtins.str","value":"num_attention_heads"},{".class":"LiteralType","fallback":"builtins.str","value":"num_channels_latents"},{".class":"LiteralType","fallback":"builtins.str","value":"in_channels"},{".class":"LiteralType","fallback":"builtins.str","value":"out_channels"},{".class":"LiteralType","fallback":"builtins.str","value":"exclude_lora_layers"},{".class":"LiteralType","fallback":"builtins.str","value":"boundary_ratio"}],"partial_fallback":{".class":"Instance","args":[{".class":"AnyType","missing_import_name":null,"source_any":null,"type_of_any":6}],"extra_attrs":null,"type_ref":"builtins.tuple"}}},"plugin_generated":true},"__mypy-post_init":{".class":"SymbolTableNode","kind":"Mdef","node":{".class":"FuncDef","abstract_status":0,"arg_kinds":[0],"arg_names":["self"],"dataclass_transform_spec":null,"deprecated":null,"flags":[],"fullname":"FastVideo.fastvideo.configs.models.dits.base.DiTArchConfig.__mypy-post_init","name":"__mypy-post_init","type":{".class":"CallableType","arg_kinds":[0],"arg_names":["self"],"arg_types":["FastVideo.fastvideo.configs.models.dits.base.DiTArchConfig"],"bound_args":[],"def_extras":{},"fallback":"builtins.function","from_concatenate":false,"implicit":false,"imprecise_arg_kinds":false,"is_ellipsis_args":false,"name":"__mypy-post_init of DiTArchConfig","ret_type":{".class":"NoneType"},"type_guard":null,"type_is":null,"unpack_kwargs":false,"variables":[]}},"plugin_generated":true},"__mypy-replace":{".class":"SymbolTableNode","kind":"Mdef","node":{".class":"Decorator","func":{".class":"FuncDef","abstract_status":0,"arg_kinds":[5,5,5,5,5,5,5,5,5,5,5,5,5],"arg_names":["_fsdp_shard_conditions","_compile_conditions","param_names_mapping","reverse_param_names_mapping","lora_param_names_mapping","_supported_attention_backends","hidden_size","num_attention_heads","num_channels_latents","in_channels","out_channels","exclude_lora_layers","boundary_ratio"],"dataclass_transform_spec":null,"deprecated":null,"flags":["is_static","is_decorated"],"fullname":"FastVideo.fastvideo.configs.models.dits.base.DiTArchConfig.__mypy-replace","name":"__mypy-replace","type":{".class":"CallableType","arg_kinds":[5,5,5,5,5,5,5,5,5,5,5,5,5],"arg_names":["_fsdp_shard_conditions","_compile_conditions","param_names_mapping","reverse_param_names_mapping","lora_param_names_mapping","_supported_attention_backends","hidden_size","num_attention_heads","num_channels_latents","in_channels","out_channels","exclude_lora_layers","boundary_ratio"],"arg_types":[{".class":"Instance","args":[{".class":"AnyType","missing_import_name":null,"source_any":null,"type_of_any":4}],"extra_attrs":null,"type_ref":"builtins.list"},{".class":"Instance","args":[{".class":"AnyType","missing_import_name":null,"source_any":null,"type_of_any":4}],"extra_attrs":null,"type_ref":"builtins.list"},{".class":"Instance","args":[{".class":"AnyType","missing_import_name":null,"source_any":null,"type_of_any":4},{".class":"AnyType","missing_import_name":null,"source_any":null,"type_of_any":4}],"extra_attrs":null,"type_ref":"builtins.dict"},{".class":"Instance","args":[{".class":"AnyType","missing_import_name":null,"source_any":null,"type_of_any":4},{".class":"AnyType","missing_import_name":null,"source_any":null,"type_of_any":4}],"extra_attrs":null,"type_ref":"builtins.dict"},{".class":"Instance","args":[{".class":"AnyType","missing_import_name":null,"source_any":null,"type_of_any":4},{".class":"AnyType","missing_import_name":null,"source_any":null,"type_of_any":4}],"extra_attrs":null,"type_ref":"builtins.dict"},{".class":"Instance","args":[{".class":"AnyType","missing_import_name":"FastVideo.fastvideo.configs.models.dits.base.AttentionBackendEnum","source_any":null,"type_of_any":3}],"extra_attrs":null,"type_ref":"builtins.tuple"},"builtins.int","builtins.int","builtins.int","builtins.int","builtins.int",{".class":"Instance","args":["builtins.str"],"extra_attrs":null,"type_ref":"builtins.list"},{".class":"UnionType","items":["builtins.float",{".class":"NoneType"}],"uses_pep604_syntax":false}],"bound_args":[],"def_extras":{},"fallback":"builtins.function","from_concatenate":false,"implicit":false,"imprecise_arg_kinds":false,"is_ellipsis_args":false,"name":"__mypy-replace of DiTArchConfig","ret_type":{".class":"NoneType"},"type_guard":null,"type_is":null,"unpack_kwargs":false,"variables":[]}},"is_overload":false,"var":{".class":"Var","flags":["is_staticmethod","is_ready"],"fullname":"FastVideo.fastvideo.configs.models.dits.base.DiTArchConfig.__mypy-replace","name":"__mypy-replace","type":{".class":"CallableType","arg_kinds":[5,5,5,5,5,5,5,5,5,5,5,5,5],"arg_names":["_fsdp_shard_conditions","_compile_conditions","param_names_mapping","reverse_param_names_mapping","lora_param_names_mapping","_supported_attention_backends","hidden_size","num_attention_heads","num_channels_latents","in_channels","out_channels","exclude_lora_layers","boundary_ratio"],"arg_types":[{".class":"Instance","args":[{".class":"AnyType","missing_import_name":null,"source_any":null,"type_of_any":4}],"extra_attrs":null,"type_ref":"builtins.list"},{".class":"Instance","args":[{".class":"AnyType","missing_import_name":null,"source_any":null,"type_of_any":4}],"extra_attrs":null,"type_ref":"builtins.list"},{".class":"Instance","args":[{".class":"AnyType","missing_import_name":null,"source_any":null,"type_of_any":4},{".class":"AnyType","missing_import_name":null,"source_any":null,"type_of_any":4}],"extra_attrs":null,"type_ref":"builtins.dict"},{".class":"Instance","args":[{".class":"AnyType","missing_import_name":null,"source_any":null,"type_of_any":4},{".class":"AnyType","missing_import_name":null,"source_any":null,"type_of_any":4}],"extra_attrs":null,"type_ref":"builtins.dict"},{".class":"Instance","args":[{".class":"AnyType","missing_import_name":null,"source_any":null,"type_of_any":4},{".class":"AnyType","missing_import_name":null,"source_any":null,"type_of_any":4}],"extra_attrs":null,"type_ref":"builtins.dict"},{".class":"Instance","args":[{".class":"AnyType","missing_import_name":"FastVideo.fastvideo.configs.models.dits.base.AttentionBackendEnum","source_any":null,"type_of_any":3}],"extra_attrs":null,"type_ref":"builtins.tuple"},"builtins.int","builtins.int","builtins.int","builtins.int","builtins.int",{".class":"Instance","args":["builtins.str"],"extra_attrs":null,"type_ref":"builtins.list"},{".class":"UnionType","items":["builtins.float",{".class":"NoneType"}],"uses_pep604_syntax":false}],"bound_args":[],"def_extras":{},"fallback":"builtins.function","from_concatenate":false,"implicit":false,"imprecise_arg_kinds":false,"is_ellipsis_args":false,"name":"__mypy-replace of DiTArchConfig","ret_type":{".class":"NoneType"},"type_guard":null,"type_is":null,"unpack_kwargs":false,"variables":[]}}},"plugin_generated":true},"__post_init__":{".class":"SymbolTableNode","kind":"Mdef","node":{".class":"FuncDef","abstract_status":0,"arg_kinds":[0],"arg_names":["self"],"dataclass_transform_spec":null,"deprecated":null,"flags":[],"fullname":"FastVideo.fastvideo.configs.models.dits.base.DiTArchConfig.__post_init__","name":"__post_init__","type":{".class":"CallableType","arg_kinds":[0],"arg_names":["self"],"arg_types":["FastVideo.fastvideo.configs.models.dits.base.DiTArchConfig"],"bound_args":[],"def_extras":{"first_arg":"self"},"fallback":"builtins.function","from_concatenate":false,"implicit":false,"imprecise_arg_kinds":false,"is_ellipsis_args":false,"name":"__post_init__ of DiTArchConfig","ret_type":{".class":"NoneType"},"type_guard":null,"type_is":null,"unpack_kwargs":false,"variables":[]}}},"_compile_conditions":{".class":"SymbolTableNode","kind":"Mdef","node":{".class":"Var","flags":["is_initialized_in_class","is_ready","has_explicit_value"],"fullname":"FastVideo.fastvideo.configs.models.dits.base.DiTArchConfig._compile_conditions","name":"_compile_conditions","type":{".class":"Instance","args":[{".class":"AnyType","missing_import_name":null,"source_any":null,"type_of_any":4}],"extra_attrs":null,"type_ref":"builtins.list"}}},"_fsdp_shard_conditions":{".class":"SymbolTableNode","kind":"Mdef","node":{".class":"Var","flags":["is_initialized_in_class","is_ready","has_explicit_value"],"fullname":"FastVideo.fastvideo.configs.models.dits.base.DiTArchConfig._fsdp_shard_conditions","name":"_fsdp_shard_conditions","type":{".class":"Instance","args":[{".class":"AnyType","missing_import_name":null,"source_any":null,"type_of_any":4}],"extra_attrs":null,"type_ref":"builtins.list"}}},"_supported_attention_backends":{".class":"SymbolTableNode","kind":"Mdef","node":{".class":"Var","flags":["is_initialized_in_class","is_ready","has_explicit_value"],"fullname":"FastVideo.fastvideo.configs.models.dits.base.DiTArchConfig._supported_attention_backends","name":"_supported_attention_backends","type":{".class":"Instance","args":[{".class":"AnyType","missing_import_name":"FastVideo.fastvideo.configs.models.dits.base.AttentionBackendEnum","source_any":null,"type_of_any":3}],"extra_attrs":null,"type_ref":"builtins.tuple"}}},"boundary_ratio":{".class":"SymbolTableNode","kind":"Mdef","node":{".class":"Var","flags":["is_initialized_in_class","is_ready","has_explicit_value"],"fullname":"FastVideo.fastvideo.configs.models.dits.base.DiTArchConfig.boundary_ratio","name":"boundary_ratio","type":{".class":"UnionType","items":["builtins.float",{".class":"NoneType"}],"uses_pep604_syntax":true}}},"exclude_lora_layers":{".class":"SymbolTableNode","kind":"Mdef","node":{".class":"Var","flags":["is_initialized_in_class","is_ready","has_explicit_value"],"fullname":"FastVideo.fastvideo.configs.models.dits.base.DiTArchConfig.exclude_lora_layers","name":"exclude_lora_layers","type":{".class":"Instance","args":["builtins.str"],"extra_attrs":null,"type_ref":"builtins.list"}}},"hidden_size":{".class":"SymbolTableNode","kind":"Mdef","node":{".class":"Var","flags":["is_initialized_in_class","is_ready","has_explicit_value"],"fullname":"FastVideo.fastvideo.configs.models.dits.base.DiTArchConfig.hidden_size","name":"hidden_size","type":"builtins.int"}},"in_channels":{".class":"SymbolTableNode","kind":"Mdef","node":{".class":"Var","flags":["is_initialized_in_class","is_ready","has_explicit_value"],"fullname":"FastVideo.fastvideo.configs.models.dits.base.DiTArchConfig.in_channels","name":"in_channels","type":"builtins.int"}},"lora_param_names_mapping":{".class":"SymbolTableNode","kind":"Mdef","node":{".class":"Var","flags":["is_initialized_in_class","is_ready","has_explicit_value"],"fullname":"FastVideo.fastvideo.configs.models.dits.base.DiTArchConfig.lora_param_names_mapping","name":"lora_param_names_mapping","type":{".class":"Instance","args":[{".class":"AnyType","missing_import_name":null,"source_any":null,"type_of_any":4},{".class":"AnyType","missing_import_name":null,"source_any":null,"type_of_any":4}],"extra_attrs":null,"type_ref":"builtins.dict"}}},"num_attention_heads":{".class":"SymbolTableNode","kind":"Mdef","node":{".class":"Var","flags":["is_initialized_in_class","is_ready","has_explicit_value"],"fullname":"FastVideo.fastvideo.configs.models.dits.base.DiTArchConfig.num_attention_heads","name":"num_attention_heads","type":"builtins.int"}},"num_channels_latents":{".class":"SymbolTableNode","kind":"Mdef","node":{".class":"Var","flags":["is_initialized_in_class","is_ready","has_explicit_value"],"fullname":"FastVideo.fastvideo.configs.models.dits.base.DiTArchConfig.num_channels_latents","name":"num_channels_latents","type":"builtins.int"}},"out_channels":{".class":"SymbolTableNode","kind":"Mdef","node":{".class":"Var","flags":["is_initialized_in_class","is_ready","has_explicit_value"],"fullname":"FastVideo.fastvideo.configs.models.dits.base.DiTArchConfig.out_channels","name":"out_channels","type":"builtins.int"}},"param_names_mapping":{".class":"SymbolTableNode","kind":"Mdef","node":{".class":"Var","flags":["is_initialized_in_class","is_ready","has_explicit_value"],"fullname":"FastVideo.fastvideo.configs.models.dits.base.DiTArchConfig.param_names_mapping","name":"param_names_mapping","type":{".class":"Instance","args":[{".class":"AnyType","missing_import_name":null,"source_any":null,"type_of_any":4},{".class":"AnyType","missing_import_name":null,"source_any":null,"type_of_any":4}],"extra_attrs":null,"type_ref":"builtins.dict"}}},"reverse_param_names_mapping":{".class":"SymbolTableNode","kind":"Mdef","node":{".class":"Var","flags":["is_initialized_in_class","is_ready","has_explicit_value"],"fullname":"FastVideo.fastvideo.configs.models.dits.base.DiTArchConfig.reverse_param_names_mapping","name":"reverse_param_names_mapping","type":{".class":"Instance","args":[{".class":"AnyType","missing_import_name":null,"source_any":null,"type_of_any":4},{".class":"AnyType","missing_import_name":null,"source_any":null,"type_of_any":4}],"extra_attrs":null,"type_ref":"builtins.dict"}}}},"self_type":{".class":"TypeVarType","default":{".class":"AnyType","missing_import_name":null,"source_any":null,"type_of_any":4},"fullname":"FastVideo.fastvideo.configs.models.dits.base.DiTArchConfig.Self","id":0,"name":"Self","namespace":"","upper_bound":"FastVideo.fastvideo.configs.models.dits.base.DiTArchConfig","values":[],"variance":0},"slots":null,"tuple_type":null,"type_vars":[],"typeddict_type":null}},"DiTConfig":{".class":"SymbolTableNode","kind":"Gdef","node":{".class":"TypeInfo","_promote":[],"abstract_attributes":[],"alt_promote":null,"bases":["builtins.object"],"dataclass_transform_spec":null,"declared_metaclass":null,"defn":{".class":"ClassDef","fullname":"FastVideo.fastvideo.configs.models.dits.base.DiTConfig","name":"DiTConfig","type_vars":[]},"deletable_attributes":[],"deprecated":null,"flags":["fallback_to_any"],"fullname":"FastVideo.fastvideo.configs.models.dits.base.DiTConfig","has_param_spec_type":false,"metaclass_type":null,"metadata":{"dataclass":{"attributes":[{"alias":null,"column":4,"has_default":true,"is_in_init":true,"is_init_var":false,"is_neither_frozen_nor_nonfrozen":false,"kw_only":false,"line":38,"name":"arch_config","type":"FastVideo.fastvideo.configs.models.dits.base.DiTArchConfig"},{"alias":null,"column":4,"has_default":true,"is_in_init":true,"is_init_var":false,"is_neither_frozen_nor_nonfrozen":false,"kw_only":false,"line":41,"name":"prefix","type":"builtins.str"},{"alias":null,"column":4,"has_default":true,"is_in_init":true,"is_init_var":false,"is_neither_frozen_nor_nonfrozen":false,"kw_only":false,"line":42,"name":"quant_config","type":{".class":"UnionType","items":[{".class":"AnyType","missing_import_name":"FastVideo.fastvideo.configs.models.dits.base.QuantizationConfig","source_any":null,"type_of_any":3},{".class":"NoneType"}],"uses_pep604_syntax":true}}],"frozen":false},"dataclass_tag":{}},"module_name":"FastVideo.fastvideo.configs.models.dits.base","mro":["FastVideo.fastvideo.configs.models.dits.base.DiTConfig","builtins.object"],"names":{".class":"SymbolTable","__dataclass_fields__":{".class":"SymbolTableNode","kind":"Mdef","node":{".class":"Var","flags":["is_classvar","is_ready"],"fullname":"FastVideo.fastvideo.configs.models.dits.base.DiTConfig.__dataclass_fields__","name":"__dataclass_fields__","type":{".class":"Instance","args":["builtins.str",{".class":"Instance","args":[{".class":"AnyType","missing_import_name":null,"source_any":null,"type_of_any":2}],"extra_attrs":null,"type_ref":"dataclasses.Field"}],"extra_attrs":null,"type_ref":"builtins.dict"}},"plugin_generated":true},"__init__":{".class":"SymbolTableNode","kind":"Mdef","node":{".class":"FuncDef","abstract_status":0,"arg_kinds":[0,2,1,1,1,4],"arg_names":["self","generated_args","arch_config","prefix","quant_config","generated_kwargs"],"dataclass_transform_spec":null,"deprecated":null,"flags":[],"fullname":"FastVideo.fastvideo.configs.models.dits.base.DiTConfig.__init__","name":"__init__","type":{".class":"CallableType","arg_kinds":[0,2,1,1,1,4],"arg_names":["self","generated_args","arch_config","prefix","quant_config","generated_kwargs"],"arg_types":["FastVideo.fastvideo.configs.models.dits.base.DiTConfig",{".class":"AnyType","missing_import_name":null,"source_any":null,"type_of_any":2},"FastVideo.fastvideo.configs.models.dits.base.DiTArchConfig","builtins.str",{".class":"UnionType","items":[{".class":"AnyType","missing_import_name":"FastVideo.fastvideo.configs.models.dits.base.QuantizationConfig","source_any":null,"type_of_any":3},{".class":"NoneType"}],"uses_pep604_syntax":false},{".class":"AnyType","missing_import_name":null,"source_any":null,"type_of_any":2}],"bound_args":[],"def_extras":{},"fallback":"builtins.function","from_concatenate":false,"implicit":false,"imprecise_arg_kinds":false,"is_ellipsis_args":false,"name":"__init__ of DiTConfig","ret_type":{".class":"NoneType"},"type_guard":null,"type_is":null,"unpack_kwargs":false,"variables":[]}},"plugin_generated":true},"__match_args__":{".class":"SymbolTableNode","kind":"Mdef","node":{".class":"Var","flags":["is_ready","allow_incompatible_override"],"fullname":"FastVideo.fastvideo.configs.models.dits.base.DiTConfig.__match_args__","name":"__match_args__","type":{".class":"TupleType","implicit":false,"items":[{".class":"LiteralType","fallback":"builtins.str","value":"arch_config"},{".class":"LiteralType","fallback":"builtins.str","value":"prefix"},{".class":"LiteralType","fallback":"builtins.str","value":"quant_config"}],"partial_fallback":{".class":"Instance","args":[{".class":"AnyType","missing_import_name":null,"source_any":null,"type_of_any":6}],"extra_attrs":null,"type_ref":"builtins.tuple"}}},"plugin_generated":true},"__mypy-replace":{".class":"SymbolTableNode","kind":"Mdef","node":{".class":"Decorator","func":{".class":"FuncDef","abstract_status":0,"arg_kinds":[5,5,5],"arg_names":["arch_config","prefix","quant_config"],"dataclass_transform_spec":null,"deprecated":null,"flags":["is_static","is_decorated"],"fullname":"FastVideo.fastvideo.configs.models.dits.base.DiTConfig.__mypy-replace","name":"__mypy-replace","type":{".class":"CallableType","arg_kinds":[5,5,5],"arg_names":["arch_config","prefix","quant_config"],"arg_types":["FastVideo.fastvideo.configs.models.dits.base.DiTArchConfig","builtins.str",{".class":"UnionType","items":[{".class":"AnyType","missing_import_name":"FastVideo.fastvideo.configs.models.dits.base.QuantizationConfig","source_any":null,"type_of_any":3},{".class":"NoneType"}],"uses_pep604_syntax":false}],"bound_args":[],"def_extras":{},"fallback":"builtins.function","from_concatenate":false,"implicit":false,"imprecise_arg_kinds":false,"is_ellipsis_args":false,"name":"__mypy-replace of DiTConfig","ret_type":{".class":"NoneType"},"type_guard":null,"type_is":null,"unpack_kwargs":false,"variables":[]}},"is_overload":false,"var":{".class":"Var","flags":["is_staticmethod","is_ready"],"fullname":"FastVideo.fastvideo.configs.models.dits.base.DiTConfig.__mypy-replace","name":"__mypy-replace","type":{".class":"CallableType","arg_kinds":[5,5,5],"arg_names":["arch_config","prefix","quant_config"],"arg_types":["FastVideo.fastvideo.configs.models.dits.base.DiTArchConfig","builtins.str",{".class":"UnionType","items":[{".class":"AnyType","missing_import_name":"FastVideo.fastvideo.configs.models.dits.base.QuantizationConfig","source_any":null,"type_of_any":3},{".class":"NoneType"}],"uses_pep604_syntax":false}],"bound_args":[],"def_extras":{},"fallback":"builtins.function","from_concatenate":false,"implicit":false,"imprecise_arg_kinds":false,"is_ellipsis_args":false,"name":"__mypy-replace of DiTConfig","ret_type":{".class":"NoneType"},"type_guard":null,"type_is":null,"unpack_kwargs":false,"variables":[]}}},"plugin_generated":true},"add_cli_args":{".class":"SymbolTableNode","kind":"Mdef","node":{".class":"Decorator","func":{".class":"FuncDef","abstract_status":0,"arg_kinds":[0,1],"arg_names":["parser","prefix"],"dataclass_transform_spec":null,"deprecated":null,"flags":["is_static","is_decorated"],"fullname":"FastVideo.fastvideo.configs.models.dits.base.DiTConfig.add_cli_args","name":"add_cli_args","type":{".class":"CallableType","arg_kinds":[0,1],"arg_names":["parser","prefix"],"arg_types":[{".class":"AnyType","missing_import_name":null,"source_any":null,"type_of_any":2},"builtins.str"],"bound_args":[],"def_extras":{"first_arg":null},"fallback":"builtins.function","from_concatenate":false,"implicit":false,"imprecise_arg_kinds":false,"is_ellipsis_args":false,"name":"add_cli_args of DiTConfig","ret_type":{".class":"AnyType","missing_import_name":null,"source_any":null,"type_of_any":2},"type_guard":null,"type_is":null,"unpack_kwargs":false,"variables":[]}},"is_overload":false,"var":{".class":"Var","flags":["is_initialized_in_class","is_staticmethod","is_ready","is_inferred"],"fullname":"FastVideo.fastvideo.configs.models.dits.base.DiTConfig.add_cli_args","name":"add_cli_args","type":{".class":"CallableType","arg_kinds":[0,1],"arg_names":["parser","prefix"],"arg_types":[{".class":"AnyType","missing_import_name":null,"source_any":null,"type_of_any":2},"builtins.str"],"bound_args":[],"def_extras":{"first_arg":null},"fallback":"builtins.function","from_concatenate":false,"implicit":false,"imprecise_arg_kinds":false,"is_ellipsis_args":false,"name":"add_cli_args of DiTConfig","ret_type":{".class":"AnyType","missing_import_name":null,"source_any":null,"type_of_any":2},"type_guard":null,"type_is":null,"unpack_kwargs":false,"variables":[]}}}},"arch_config":{".class":"SymbolTableNode","kind":"Mdef","node":{".class":"Var","flags":["is_initialized_in_class","is_ready","has_explicit_value"],"fullname":"FastVideo.fastvideo.configs.models.dits.base.DiTConfig.arch_config","name":"arch_config","type":"FastVideo.fastvideo.configs.models.dits.base.DiTArchConfig"}},"prefix":{".class":"SymbolTableNode","kind":"Mdef","node":{".class":"Var","flags":["is_initialized_in_class","is_ready","has_explicit_value"],"fullname":"FastVideo.fastvideo.configs.models.dits.base.DiTConfig.prefix","name":"prefix","type":"builtins.str"}},"quant_config":{".class":"SymbolTableNode","kind":"Mdef","node":{".class":"Var","flags":["is_initialized_in_class","is_ready","has_explicit_value"],"fullname":"FastVideo.fastvideo.configs.models.dits.base.DiTConfig.quant_config","name":"quant_config","type":{".class":"UnionType","items":[{".class":"AnyType","missing_import_name":"FastVideo.fastvideo.configs.models.dits.base.QuantizationConfig","source_any":null,"type_of_any":3},{".class":"NoneType"}],"uses_pep604_syntax":true}}}},"self_type":{".class":"TypeVarType","default":{".class":"AnyType","missing_import_name":null,"source_any":null,"type_of_any":4},"fullname":"FastVideo.fastvideo.configs.models.dits.base.DiTConfig.Self","id":0,"name":"Self","namespace":"","upper_bound":"FastVideo.fastvideo.configs.models.dits.base.DiTConfig","values":[],"variance":0},"slots":null,"tuple_type":null,"type_vars":[],"typeddict_type":null}},"ModelConfig":{".class":"SymbolTableNode","kind":"Gdef","node":{".class":"Var","flags":["is_suppressed_import","is_ready","is_inferred"],"fullname":"FastVideo.fastvideo.configs.models.dits.base.ModelConfig","name":"ModelConfig","type":{".class":"AnyType","missing_import_name":"FastVideo.fastvideo.configs.models.dits.base.ModelConfig","source_any":null,"type_of_any":3}}},"QuantizationConfig":{".class":"SymbolTableNode","kind":"Gdef","node":{".class":"Var","flags":["is_suppressed_import","is_ready","is_inferred"],"fullname":"FastVideo.fastvideo.configs.models.dits.base.QuantizationConfig","name":"QuantizationConfig","type":{".class":"AnyType","missing_import_name":"FastVideo.fastvideo.configs.models.dits.base.QuantizationConfig","source_any":null,"type_of_any":3}}},"__annotations__":{".class":"SymbolTableNode","kind":"Gdef","node":{".class":"Var","flags":["is_ready"],"fullname":"FastVideo.fastvideo.configs.models.dits.base.__annotations__","name":"__annotations__","type":{".class":"Instance","args":["builtins.str",{".class":"AnyType","missing_import_name":null,"source_any":null,"type_of_any":6}],"extra_attrs":null,"type_ref":"builtins.dict"}}},"__doc__":{".class":"SymbolTableNode","kind":"Gdef","node":{".class":"Var","flags":["is_ready"],"fullname":"FastVideo.fastvideo.configs.models.dits.base.__doc__","name":"__doc__","type":"builtins.str"}},"__file__":{".class":"SymbolTableNode","kind":"Gdef","node":{".class":"Var","flags":["is_ready"],"fullname":"FastVideo.fastvideo.configs.models.dits.base.__file__","name":"__file__","type":"builtins.str"}},"__name__":{".class":"SymbolTableNode","kind":"Gdef","node":{".class":"Var","flags":["is_ready"],"fullname":"FastVideo.fastvideo.configs.models.dits.base.__name__","name":"__name__","type":"builtins.str"}},"__package__":{".class":"SymbolTableNode","kind":"Gdef","node":{".class":"Var","flags":["is_ready"],"fullname":"FastVideo.fastvideo.configs.models.dits.base.__package__","name":"__package__","type":"builtins.str"}},"__spec__":{".class":"SymbolTableNode","kind":"Gdef","node":{".class":"Var","flags":["is_ready"],"fullname":"FastVideo.fastvideo.configs.models.dits.base.__spec__","name":"__spec__","type":"_frozen_importlib.ModuleSpec"}},"dataclass":{".class":"SymbolTableNode","cross_ref":"dataclasses.dataclass","kind":"Gdef"},"field":{".class":"SymbolTableNode","cross_ref":"dataclasses.field","kind":"Gdef"}},"path":"fastvideo/configs/models/dits/base.py"}