{".class":"MypyFile","_fullname":"FastVideo.fastvideo.configs.models.vaes.autoencoder_kl","future_import_flags":[],"is_partial_stub_package":false,"is_stub":false,"names":{".class":"SymbolTable","AutoencoderKLArchConfig":{".class":"SymbolTableNode","kind":"Gdef","node":{".class":"TypeInfo","_promote":[],"abstract_attributes":[],"alt_promote":null,"bases":["builtins.object"],"dataclass_transform_spec":null,"declared_metaclass":null,"defn":{".class":"ClassDef","fullname":"FastVideo.fastvideo.configs.models.vaes.autoencoder_kl.AutoencoderKLArchConfig","name":"AutoencoderKLArchConfig","type_vars":[]},"deletable_attributes":[],"deprecated":null,"flags":["fallback_to_any"],"fullname":"FastVideo.fastvideo.configs.models.vaes.autoencoder_kl.AutoencoderKLArchConfig","has_param_spec_type":false,"metaclass_type":null,"metadata":{"dataclass":{"attributes":[{"alias":null,"column":4,"has_default":true,"is_in_init":true,"is_init_var":false,"is_neither_frozen_nor_nonfrozen":false,"kw_only":false,"line":12,"name":"_name_or_path","type":"builtins.str"},{"alias":null,"column":4,"has_default":true,"is_in_init":true,"is_init_var":false,"is_neither_frozen_nor_nonfrozen":false,"kw_only":false,"line":13,"name":"act_fn","type":"builtins.str"},{"alias":null,"column":4,"has_default":true,"is_in_init":true,"is_init_var":false,"is_neither_frozen_nor_nonfrozen":false,"kw_only":false,"line":14,"name":"block_out_channels","type":{".class":"UnionType","items":[{".class":"Instance","args":["builtins.int"],"extra_attrs":null,"type_ref":"builtins.tuple"},{".class":"Instance","args":["builtins.int"],"extra_attrs":null,"type_ref":"builtins.list"}],"uses_pep604_syntax":true}},{"alias":null,"column":4,"has_default":true,"is_in_init":true,"is_init_var":false,"is_neither_frozen_nor_nonfrozen":false,"kw_only":false,"line":16,"name":"down_block_types","type":{".class":"UnionType","items":[{".class":"Instance","args":["builtins.str"],"extra_attrs":null,"type_ref":"builtins.tuple"},{".class":"Instance","args":["builtins.str"],"extra_attrs":null,"type_ref":"builtins.list"}],"uses_pep604_syntax":true}},{"alias":null,"column":4,"has_default":true,"is_in_init":true,"is_init_var":false,"is_neither_frozen_nor_nonfrozen":false,"kw_only":false,"line":17,"name":"up_block_types","type":{".class":"UnionType","items":[{".class":"Instance","args":["builtins.str"],"extra_attrs":null,"type_ref":"builtins.tuple"},{".class":"Instance","args":["builtins.str"],"extra_attrs":null,"type_ref":"builtins.list"}],"uses_pep604_syntax":true}},{"alias":null,"column":4,"has_default":true,"is_in_init":true,"is_init_var":false,"is_neither_frozen_nor_nonfrozen":false,"kw_only":false,"line":18,"name":"force_upcast","type":"builtins.bool"},{"alias":null,"column":4,"has_default":true,"is_in_init":true,"is_init_var":false,"is_neither_frozen_nor_nonfrozen":false,"kw_only":false,"line":19,"name":"in_channels","type":"builtins.int"},{"alias":null,"column":4,"has_default":true,"is_in_init":true,"is_init_var":false,"is_neither_frozen_nor_nonfrozen":false,"kw_only":false,"line":20,"name":"latent_channels","type":"builtins.int"},{"alias":null,"column":4,"has_default":true,"is_in_init":true,"is_init_var":false,"is_neither_frozen_nor_nonfrozen":false,"kw_only":false,"line":21,"name":"latents_mean","type":{".class":"UnionType","items":[{".class":"Instance","args":["builtins.float"],"extra_attrs":null,"type_ref":"builtins.tuple"},{".class":"Instance","args":["builtins.float"],"extra_attrs":null,"type_ref":"builtins.list"},{".class":"NoneType"}],"uses_pep604_syntax":true}},{"alias":null,"column":4,"has_default":true,"is_in_init":true,"is_init_var":false,"is_neither_frozen_nor_nonfrozen":false,"kw_only":false,"line":22,"name":"latents_std","type":{".class":"UnionType","items":[{".class":"Instance","args":["builtins.float"],"extra_attrs":null,"type_ref":"builtins.tuple"},{".class":"Instance","args":["builtins.float"],"extra_attrs":null,"type_ref":"builtins.list"},{".class":"NoneType"}],"uses_pep604_syntax":true}},{"alias":null,"column":4,"has_default":true,"is_in_init":true,"is_init_var":false,"is_neither_frozen_nor_nonfrozen":false,"kw_only":false,"line":23,"name":"layers_per_block","type":"builtins.int"},{"alias":null,"column":4,"has_default":true,"is_in_init":true,"is_init_var":false,"is_neither_frozen_nor_nonfrozen":false,"kw_only":false,"line":24,"name":"mid_block_add_attention","type":"builtins.bool"},{"alias":null,"column":4,"has_default":true,"is_in_init":true,"is_init_var":false,"is_neither_frozen_nor_nonfrozen":false,"kw_only":false,"line":25,"name":"norm_num_groups","type":"builtins.int"},{"alias":null,"column":4,"has_default":true,"is_in_init":true,"is_init_var":false,"is_neither_frozen_nor_nonfrozen":false,"kw_only":false,"line":26,"name":"out_channels","type":"builtins.int"},{"alias":null,"column":4,"has_default":true,"is_in_init":true,"is_init_var":false,"is_neither_frozen_nor_nonfrozen":false,"kw_only":false,"line":27,"name":"sample_size","type":"builtins.int"},{"alias":null,"column":4,"has_default":true,"is_in_init":true,"is_init_var":false,"is_neither_frozen_nor_nonfrozen":false,"kw_only":false,"line":28,"name":"scaling_factor","type":{".class":"UnionType","items":["builtins.float",{".class":"AnyType","missing_import_name":"FastVideo.fastvideo.configs.models.vaes.autoencoder_kl.torch","source_any":null,"type_of_any":3}],"uses_pep604_syntax":true}},{"alias":null,"column":4,"has_default":true,"is_in_init":true,"is_init_var":false,"is_neither_frozen_nor_nonfrozen":false,"kw_only":false,"line":29,"name":"shift_factor","type":{".class":"UnionType","items":["builtins.float",{".class":"NoneType"}],"uses_pep604_syntax":true}},{"alias":null,"column":4,"has_default":true,"is_in_init":true,"is_init_var":false,"is_neither_frozen_nor_nonfrozen":false,"kw_only":false,"line":30,"name":"use_post_quant_conv","type":"builtins.bool"},{"alias":null,"column":4,"has_default":true,"is_in_init":true,"is_init_var":false,"is_neither_frozen_nor_nonfrozen":false,"kw_only":false,"line":31,"name":"use_quant_conv","type":"builtins.bool"},{"alias":null,"column":4,"has_default":true,"is_in_init":true,"is_init_var":false,"is_neither_frozen_nor_nonfrozen":false,"kw_only":false,"line":33,"name":"temporal_compression_ratio","type":"builtins.int"},{"alias":null,"column":4,"has_default":true,"is_in_init":true,"is_init_var":false,"is_neither_frozen_nor_nonfrozen":false,"kw_only":false,"line":34,"name":"spatial_compression_ratio","type":"builtins.int"}],"frozen":false},"dataclass_tag":{}},"module_name":"FastVideo.fastvideo.configs.models.vaes.autoencoder_kl","mro":["FastVideo.fastvideo.configs.models.vaes.autoencoder_kl.AutoencoderKLArchConfig","builtins.object"],"names":{".class":"SymbolTable","__dataclass_fields__":{".class":"SymbolTableNode","kind":"Mdef","node":{".class":"Var","flags":["is_classvar","is_ready"],"fullname":"FastVideo.fastvideo.configs.models.vaes.autoencoder_kl.AutoencoderKLArchConfig.__dataclass_fields__","name":"__dataclass_fields__","type":{".class":"Instance","args":["builtins.str",{".class":"Instance","args":[{".class":"AnyType","missing_import_name":null,"source_any":null,"type_of_any":2}],"extra_attrs":null,"type_ref":"dataclasses.Field"}],"extra_attrs":null,"type_ref":"builtins.dict"}},"plugin_generated":true},"__init__":{".class":"SymbolTableNode","kind":"Mdef","node":{".class":"FuncDef","abstract_status":0,"arg_kinds":[0,2,1,1,1,1,1,1,1,1,1,1,1,1,1,1,1,1,1,1,1,1,1,4],"arg_names":["self","generated_args","_name_or_path","act_fn","block_out_channels","down_block_types","up_block_types","force_upcast","in_channels","latent_channels","latents_mean","latents_std","layers_per_block","mid_block_add_attention","norm_num_groups","out_channels","sample_size","scaling_factor","shift_factor","use_post_quant_conv","use_quant_conv","temporal_compression_ratio","spatial_compression_ratio","generated_kwargs"],"dataclass_transform_spec":null,"deprecated":null,"flags":[],"fullname":"FastVideo.fastvideo.configs.models.vaes.autoencoder_kl.AutoencoderKLArchConfig.__init__","name":"__init__","type":{".class":"CallableType","arg_kinds":[0,2,1,1,1,1,1,1,1,1,1,1,1,1,1,1,1,1,1,1,1,1,1,4],"arg_names":["self","generated_args","_name_or_path","act_fn","block_out_channels","down_block_types","up_block_types","force_upcast","in_channels","latent_channels","latents_mean","latents_std","layers_per_block","mid_block_add_attention","norm_num_groups","out_channels","sample_size","scaling_factor","shift_factor","use_post_quant_conv","use_quant_conv","temporal_compression_ratio","spatial_compression_ratio","generated_kwargs"],"arg_types":["FastVideo.fastvideo.configs.models.vaes.autoencoder_kl.AutoencoderKLArchConfig",{".class":"AnyType","missing_import_name":null,"source_any":null,"type_of_any":2},"builtins.str","builtins.str",{".class":"UnionType","items":[{".class":"Instance","args":["builtins.int"],"extra_attrs":null,"type_ref":"builtins.tuple"},{".class":"Instance","args":["builtins.int"],"extra_attrs":null,"type_ref":"builtins.list"}],"uses_pep604_syntax":false},{".class":"UnionType","items":[{".class":"Instance","args":["builtins.str"],"extra_attrs":null,"type_ref":"builtins.tuple"},{".class":"Instance","args":["builtins.str"],"extra_attrs":null,"type_ref":"builtins.list"}],"uses_pep604_syntax":false},{".class":"UnionType","items":[{".class":"Instance","args":["builtins.str"],"extra_attrs":null,"type_ref":"builtins.tuple"},{".class":"Instance","args":["builtins.str"],"extra_attrs":null,"type_ref":"builtins.list"}],"uses_pep604_syntax":false},"builtins.bool","builtins.int","builtins.int",{".class":"UnionType","items":[{".class":"Instance","args":["builtins.float"],"extra_attrs":null,"type_ref":"builtins.tuple"},{".class":"Instance","args":["builtins.float"],"extra_attrs":null,"type_ref":"builtins.list"},{".class":"NoneType"}],"uses_pep604_syntax":false},{".class":"UnionType","items":[{".class":"Instance","args":["builtins.float"],"extra_attrs":null,"type_ref":"builtins.tuple"},{".class":"Instance","args":["builtins.float"],"extra_attrs":null,"type_ref":"builtins.list"},{".class":"NoneType"}],"uses_pep604_syntax":false},"builtins.int","builtins.bool","builtins.int","builtins.int","builtins.int",{".class":"UnionType","items":["builtins.float",{".class":"AnyType","missing_import_name":"FastVideo.fastvideo.configs.models.vaes.autoencoder_kl.torch","source_any":null,"type_of_any":3}],"uses_pep604_syntax":false},{".class":"UnionType","items":["builtins.float",{".class":"NoneType"}],"uses_pep604_syntax":false},"builtins.bool","builtins.bool","builtins.int","builtins.int",{".class":"AnyType","missing_import_name":null,"source_any":null,"type_of_any":2}],"bound_args":[],"def_extras":{},"fallback":"builtins.function","from_concatenate":false,"implicit":false,"imprecise_arg_kinds":false,"is_ellipsis_args":false,"name":"__init__ of AutoencoderKLArchConfig","ret_type":{".class":"NoneType"},"type_guard":null,"type_is":null,"unpack_kwargs":false,"variables":[]}},"plugin_generated":true},"__match_args__":{".class":"SymbolTableNode","kind":"Mdef","node":{".class":"Var","flags":["is_ready","allow_incompatible_override"],"fullname":"FastVideo.fastvideo.configs.models.vaes.autoencoder_kl.AutoencoderKLArchConfig.__match_args__","name":"__match_args__","type":{".class":"TupleType","implicit":false,"items":[{".class":"LiteralType","fallback":"builtins.str","value":"_name_or_path"},{".class":"LiteralType","fallback":"builtins.str","value":"act_fn"},{".class":"LiteralType","fallback":"builtins.str","value":"block_out_channels"},{".class":"LiteralType","fallback":"builtins.str","value":"down_block_types"},{".class":"LiteralType","fallback":"builtins.str","value":"up_block_types"},{".class":"LiteralType","fallback":"builtins.str","value":"force_upcast"},{".class":"LiteralType","fallback":"builtins.str","value":"in_channels"},{".class":"LiteralType","fallback":"builtins.str","value":"latent_channels"},{".class":"LiteralType","fallback":"builtins.str","value":"latents_mean"},{".class":"LiteralType","fallback":"builtins.str","value":"latents_std"},{".class":"LiteralType","fallback":"builtins.str","value":"layers_per_block"},{".class":"LiteralType","fallback":"builtins.str","value":"mid_block_add_attention"},{".class":"LiteralType","fallback":"builtins.str","value":"norm_num_groups"},{".class":"LiteralType","fallback":"builtins.str","value":"out_channels"},{".class":"LiteralType","fallback":"builtins.str","value":"sample_size"},{".class":"LiteralType","fallback":"builtins.str","value":"scaling_factor"},{".class":"LiteralType","fallback":"builtins.str","value":"shift_factor"},{".class":"LiteralType","fallback":"builtins.str","value":"use_post_quant_conv"},{".class":"LiteralType","fallback":"builtins.str","value":"use_quant_conv"},{".class":"LiteralType","fallback":"builtins.str","value":"temporal_compression_ratio"},{".class":"LiteralType","fallback":"builtins.str","value":"spatial_compression_ratio"}],"partial_fallback":{".class":"Instance","args":[{".class":"AnyType","missing_import_name":null,"source_any":null,"type_of_any":6}],"extra_attrs":null,"type_ref":"builtins.tuple"}}},"plugin_generated":true},"__mypy-replace":{".class":"SymbolTableNode","kind":"Mdef","node":{".class":"Decorator","func":{".class":"FuncDef","abstract_status":0,"arg_kinds":[5,5,5,5,5,5,5,5,5,5,5,5,5,5,5,5,5,5,5,5,5],"arg_names":["_name_or_path","act_fn","block_out_channels","down_block_types","up_block_types","force_upcast","in_channels","latent_channels","latents_mean","latents_std","layers_per_block","mid_block_add_attention","norm_num_groups","out_channels","sample_size","scaling_factor","shift_factor","use_post_quant_conv","use_quant_conv","temporal_compression_ratio","spatial_compression_ratio"],"dataclass_transform_spec":null,"deprecated":null,"flags":["is_static","is_decorated"],"fullname":"FastVideo.fastvideo.configs.models.vaes.autoencoder_kl.AutoencoderKLArchConfig.__mypy-replace","name":"__mypy-replace","type":{".class":"CallableType","arg_kinds":[5,5,5,5,5,5,5,5,5,5,5,5,5,5,5,5,5,5,5,5,5],"arg_names":["_name_or_path","act_fn","block_out_channels","down_block_types","up_block_types","force_upcast","in_channels","latent_channels","latents_mean","latents_std","layers_per_block","mid_block_add_attention","norm_num_groups","out_channels","sample_size","scaling_factor","shift_factor","use_post_quant_conv","use_quant_conv","temporal_compression_ratio","spatial_compression_ratio"],"arg_types":["builtins.str","builtins.str",{".class":"UnionType","items":[{".class":"Instance","args":["builtins.int"],"extra_attrs":null,"type_ref":"builtins.tuple"},{".class":"Instance","args":["builtins.int"],"extra_attrs":null,"type_ref":"builtins.list"}],"uses_pep604_syntax":false},{".class":"UnionType","items":[{".class":"Instance","args":["builtins.str"],"extra_attrs":null,"type_ref":"builtins.tuple"},{".class":"Instance","args":["builtins.str"],"extra_attrs":null,"type_ref":"builtins.list"}],"uses_pep604_syntax":false},{".class":"UnionType","items":[{".class":"Instance","args":["builtins.str"],"extra_attrs":null,"type_ref":"builtins.tuple"},{".class":"Instance","args":["builtins.str"],"extra_attrs":null,"type_ref":"builtins.list"}],"uses_pep604_syntax":false},"builtins.bool","builtins.int","builtins.int",{".class":"UnionType","items":[{".class":"Instance","args":["builtins.float"],"extra_attrs":null,"type_ref":"builtins.tuple"},{".class":"Instance","args":["builtins.float"],"extra_attrs":null,"type_ref":"builtins.list"},{".class":"NoneType"}],"uses_pep604_syntax":false},{".class":"UnionType","items":[{".class":"Instance","args":["builtins.float"],"extra_attrs":null,"type_ref":"builtins.tuple"},{".class":"Instance","args":["builtins.float"],"extra_attrs":null,"type_ref":"builtins.list"},{".class":"NoneType"}],"uses_pep604_syntax":false},"builtins.int","builtins.bool","builtins.int","builtins.int","builtins.int",{".class":"UnionType","items":["builtins.float",{".class":"AnyType","missing_import_name":"FastVideo.fastvideo.configs.models.vaes.autoencoder_kl.torch","source_any":null,"type_of_any":3}],"uses_pep604_syntax":false},{".class":"UnionType","items":["builtins.float",{".class":"NoneType"}],"uses_pep604_syntax":false},"builtins.bool","builtins.bool","builtins.int","builtins.int"],"bound_args":[],"def_extras":{},"fallback":"builtins.function","from_concatenate":false,"implicit":false,"imprecise_arg_kinds":false,"is_ellipsis_args":false,"name":"__mypy-replace of AutoencoderKLArchConfig","ret_type":{".class":"NoneType"},"type_guard":null,"type_is":null,"unpack_kwargs":false,"variables":[]}},"is_overload":false,"var":{".class":"Var","flags":["is_staticmethod","is_ready"],"fullname":"FastVideo.fastvideo.configs.models.vaes.autoencoder_kl.AutoencoderKLArchConfig.__mypy-replace","name":"__mypy-replace","type":{".class":"CallableType","arg_kinds":[5,5,5,5,5,5,5,5,5,5,5,5,5,5,5,5,5,5,5,5,5],"arg_names":["_name_or_path","act_fn","block_out_channels","down_block_types","up_block_types","force_upcast","in_channels","latent_channels","latents_mean","latents_std","layers_per_block","mid_block_add_attention","norm_num_groups","out_channels","sample_size","scaling_factor","shift_factor","use_post_quant_conv","use_quant_conv","temporal_compression_ratio","spatial_compression_ratio"],"arg_types":["builtins.str","builtins.str",{".class":"UnionType","items":[{".class":"Instance","args":["builtins.int"],"extra_attrs":null,"type_ref":"builtins.tuple"},{".class":"Instance","args":["builtins.int"],"extra_attrs":null,"type_ref":"builtins.list"}],"uses_pep604_syntax":false},{".class":"UnionType","items":[{".class":"Instance","args":["builtins.str"],"extra_attrs":null,"type_ref":"builtins.tuple"},{".class":"Instance","args":["builtins.str"],"extra_attrs":null,"type_ref":"builtins.list"}],"uses_pep604_syntax":false},{".class":"UnionType","items":[{".class":"Instance","args":["builtins.str"],"extra_attrs":null,"type_ref":"builtins.tuple"},{".class":"Instance","args":["builtins.str"],"extra_attrs":null,"type_ref":"builtins.list"}],"uses_pep604_syntax":false},"builtins.bool","builtins.int","builtins.int",{".class":"UnionType","items":[{".class":"Instance","args":["builtins.float"],"extra_attrs":null,"type_ref":"builtins.tuple"},{".class":"Instance","args":["builtins.float"],"extra_attrs":null,"type_ref":"builtins.list"},{".class":"NoneType"}],"uses_pep604_syntax":false},{".class":"UnionType","items":[{".class":"Instance","args":["builtins.float"],"extra_attrs":null,"type_ref":"builtins.tuple"},{".class":"Instance","args":["builtins.float"],"extra_attrs":null,"type_ref":"builtins.list"},{".class":"NoneType"}],"uses_pep604_syntax":false},"builtins.int","builtins.bool","builtins.int","builtins.int","builtins.int",{".class":"UnionType","items":["builtins.float",{".class":"AnyType","missing_import_name":"FastVideo.fastvideo.configs.models.vaes.autoencoder_kl.torch","source_any":null,"type_of_any":3}],"uses_pep604_syntax":false},{".class":"UnionType","items":["builtins.float",{".class":"NoneType"}],"uses_pep604_syntax":false},"builtins.bool","builtins.bool","builtins.int","builtins.int"],"bound_args":[],"def_extras":{},"fallback":"builtins.function","from_concatenate":false,"implicit":false,"imprecise_arg_kinds":false,"is_ellipsis_args":false,"name":"__mypy-replace of AutoencoderKLArchConfig","ret_type":{".class":"NoneType"},"type_guard":null,"type_is":null,"unpack_kwargs":false,"variables":[]}}},"plugin_generated":true},"_name_or_path":{".class":"SymbolTableNode","kind":"Mdef","node":{".class":"Var","flags":["is_initialized_in_class","is_ready","has_explicit_value"],"fullname":"FastVideo.fastvideo.configs.models.vaes.autoencoder_kl.AutoencoderKLArchConfig._name_or_path","name":"_name_or_path","type":"builtins.str"}},"act_fn":{".class":"SymbolTableNode","kind":"Mdef","node":{".class":"Var","flags":["is_initialized_in_class","is_ready","has_explicit_value"],"fullname":"FastVideo.fastvideo.configs.models.vaes.autoencoder_kl.AutoencoderKLArchConfig.act_fn","name":"act_fn","type":"builtins.str"}},"block_out_channels":{".class":"SymbolTableNode","kind":"Mdef","node":{".class":"Var","flags":["is_initialized_in_class","is_ready","has_explicit_value"],"fullname":"FastVideo.fastvideo.configs.models.vaes.autoencoder_kl.AutoencoderKLArchConfig.block_out_channels","name":"block_out_channels","type":{".class":"UnionType","items":[{".class":"Instance","args":["builtins.int"],"extra_attrs":null,"type_ref":"builtins.tuple"},{".class":"Instance","args":["builtins.int"],"extra_attrs":null,"type_ref":"builtins.list"}],"uses_pep604_syntax":true}}},"down_block_types":{".class":"SymbolTableNode","kind":"Mdef","node":{".class":"Var","flags":["is_initialized_in_class","is_ready","has_explicit_value"],"fullname":"FastVideo.fastvideo.configs.models.vaes.autoencoder_kl.AutoencoderKLArchConfig.down_block_types","name":"down_block_types","type":{".class":"UnionType","items":[{".class":"Instance","args":["builtins.str"],"extra_attrs":null,"type_ref":"builtins.tuple"},{".class":"Instance","args":["builtins.str"],"extra_attrs":null,"type_ref":"builtins.list"}],"uses_pep604_syntax":true}}},"force_upcast":{".class":"SymbolTableNode","kind":"Mdef","node":{".class":"Var","flags":["is_initialized_in_class","is_ready","has_explicit_value"],"fullname":"FastVideo.fastvideo.configs.models.vaes.autoencoder_kl.AutoencoderKLArchConfig.force_upcast","name":"force_upcast","type":"builtins.bool"}},"in_channels":{".class":"SymbolTableNode","kind":"Mdef","node":{".class":"Var","flags":["is_initialized_in_class","is_ready","has_explicit_value"],"fullname":"FastVideo.fastvideo.configs.models.vaes.autoencoder_kl.AutoencoderKLArchConfig.in_channels","name":"in_channels","type":"builtins.int"}},"latent_channels":{".class":"SymbolTableNode","kind":"Mdef","node":{".class":"Var","flags":["is_initialized_in_class","is_ready","has_explicit_value"],"fullname":"FastVideo.fastvideo.configs.models.vaes.autoencoder_kl.AutoencoderKLArchConfig.latent_channels","name":"latent_channels","type":"builtins.int"}},"latents_mean":{".class":"SymbolTableNode","kind":"Mdef","node":{".class":"Var","flags":["is_initialized_in_class","is_ready","has_explicit_value"],"fullname":"FastVideo.fastvideo.configs.models.vaes.autoencoder_kl.AutoencoderKLArchConfig.latents_mean","name":"latents_mean","type":{".class":"UnionType","items":[{".class":"Instance","args":["builtins.float"],"extra_attrs":null,"type_ref":"builtins.tuple"},{".class":"Instance","args":["builtins.float"],"extra_attrs":null,"type_ref":"builtins.list"},{".class":"NoneType"}],"uses_pep604_syntax":true}}},"latents_std":{".class":"SymbolTableNode","kind":"Mdef","node":{".class":"Var","flags":["is_initialized_in_class","is_ready","has_explicit_value"],"fullname":"FastVideo.fastvideo.configs.models.vaes.autoencoder_kl.AutoencoderKLArchConfig.latents_std","name":"latents_std","type":{".class":"UnionType","items":[{".class":"Instance","args":["builtins.float"],"extra_attrs":null,"type_ref":"builtins.tuple"},{".class":"Instance","args":["builtins.float"],"extra_attrs":null,"type_ref":"builtins.list"},{".class":"NoneType"}],"uses_pep604_syntax":true}}},"layers_per_block":{".class":"SymbolTableNode","kind":"Mdef","node":{".class":"Var","flags":["is_initialized_in_class","is_ready","has_explicit_value"],"fullname":"FastVideo.fastvideo.configs.models.vaes.autoencoder_kl.AutoencoderKLArchConfig.layers_per_block","name":"layers_per_block","type":"builtins.int"}},"mid_block_add_attention":{".class":"SymbolTableNode","kind":"Mdef","node":{".class":"Var","flags":["is_initialized_in_class","is_ready","has_explicit_value"],"fullname":"FastVideo.fastvideo.configs.models.vaes.autoencoder_kl.AutoencoderKLArchConfig.mid_block_add_attention","name":"mid_block_add_attention","type":"builtins.bool"}},"norm_num_groups":{".class":"SymbolTableNode","kind":"Mdef","node":{".class":"Var","flags":["is_initialized_in_class","is_ready","has_explicit_value"],"fullname":"FastVideo.fastvideo.configs.models.vaes.autoencoder_kl.AutoencoderKLArchConfig.norm_num_groups","name":"norm_num_groups","type":"builtins.int"}},"out_channels":{".class":"SymbolTableNode","kind":"Mdef","node":{".class":"Var","flags":["is_initialized_in_class","is_ready","has_explicit_value"],"fullname":"FastVideo.fastvideo.configs.models.vaes.autoencoder_kl.AutoencoderKLArchConfig.out_channels","name":"out_channels","type":"builtins.int"}},"sample_size":{".class":"SymbolTableNode","kind":"Mdef","node":{".class":"Var","flags":["is_initialized_in_class","is_ready","has_explicit_value"],"fullname":"FastVideo.fastvideo.configs.models.vaes.autoencoder_kl.AutoencoderKLArchConfig.sample_size","name":"sample_size","type":"builtins.int"}},"scaling_factor":{".class":"SymbolTableNode","kind":"Mdef","node":{".class":"Var","flags":["is_initialized_in_class","is_ready","has_explicit_value"],"fullname":"FastVideo.fastvideo.configs.models.vaes.autoencoder_kl.AutoencoderKLArchConfig.scaling_factor","name":"scaling_factor","type":{".class":"UnionType","items":["builtins.float",{".class":"AnyType","missing_import_name":"FastVideo.fastvideo.configs.models.vaes.autoencoder_kl.torch","source_any":null,"type_of_any":3}],"uses_pep604_syntax":true}}},"shift_factor":{".class":"SymbolTableNode","kind":"Mdef","node":{".class":"Var","flags":["is_initialized_in_class","is_ready","has_explicit_value"],"fullname":"FastVideo.fastvideo.configs.models.vaes.autoencoder_kl.AutoencoderKLArchConfig.shift_factor","name":"shift_factor","type":{".class":"UnionType","items":["builtins.float",{".class":"NoneType"}],"uses_pep604_syntax":true}}},"spatial_compression_ratio":{".class":"SymbolTableNode","kind":"Mdef","node":{".class":"Var","flags":["is_initialized_in_class","is_ready","has_explicit_value"],"fullname":"FastVideo.fastvideo.configs.models.vaes.autoencoder_kl.AutoencoderKLArchConfig.spatial_compression_ratio","name":"spatial_compression_ratio","type":"builtins.int"}},"temporal_compression_ratio":{".class":"SymbolTableNode","kind":"Mdef","node":{".class":"Var","flags":["is_initialized_in_class","is_ready","has_explicit_value"],"fullname":"FastVideo.fastvideo.configs.models.vaes.autoencoder_kl.AutoencoderKLArchConfig.temporal_compression_ratio","name":"temporal_compression_ratio","type":"builtins.int"}},"up_block_types":{".class":"SymbolTableNode","kind":"Mdef","node":{".class":"Var","flags":["is_initialized_in_class","is_ready","has_explicit_value"],"fullname":"FastVideo.fastvideo.configs.models.vaes.autoencoder_kl.AutoencoderKLArchConfig.up_block_types","name":"up_block_types","type":{".class":"UnionType","items":[{".class":"Instance","args":["builtins.str"],"extra_attrs":null,"type_ref":"builtins.tuple"},{".class":"Instance","args":["builtins.str"],"extra_attrs":null,"type_ref":"builtins.list"}],"uses_pep604_syntax":true}}},"use_post_quant_conv":{".class":"SymbolTableNode","kind":"Mdef","node":{".class":"Var","flags":["is_initialized_in_class","is_ready","has_explicit_value"],"fullname":"FastVideo.fastvideo.configs.models.vaes.autoencoder_kl.AutoencoderKLArchConfig.use_post_quant_conv","name":"use_post_quant_conv","type":"builtins.bool"}},"use_quant_conv":{".class":"SymbolTableNode","kind":"Mdef","node":{".class":"Var","flags":["is_initialized_in_class","is_ready","has_explicit_value"],"fullname":"FastVideo.fastvideo.configs.models.vaes.autoencoder_kl.AutoencoderKLArchConfig.use_quant_conv","name":"use_quant_conv","type":"builtins.bool"}}},"self_type":{".class":"TypeVarType","default":{".class":"AnyType","missing_import_name":null,"source_any":null,"type_of_any":4},"fullname":"FastVideo.fastvideo.configs.models.vaes.autoencoder_kl.AutoencoderKLArchConfig.Self","id":0,"name":"Self","namespace":"","upper_bound":"FastVideo.fastvideo.configs.models.vaes.autoencoder_kl.AutoencoderKLArchConfig","values":[],"variance":0},"slots":null,"tuple_type":null,"type_vars":[],"typeddict_type":null}},"AutoencoderKLVAEConfig":{".class":"SymbolTableNode","kind":"Gdef","node":{".class":"TypeInfo","_promote":[],"abstract_attributes":[],"alt_promote":null,"bases":["builtins.object"],"dataclass_transform_spec":null,"declared_metaclass":null,"defn":{".class":"ClassDef","fullname":"FastVideo.fastvideo.configs.models.vaes.autoencoder_kl.AutoencoderKLVAEConfig","name":"AutoencoderKLVAEConfig","type_vars":[]},"deletable_attributes":[],"deprecated":null,"flags":["fallback_to_any"],"fullname":"FastVideo.fastvideo.configs.models.vaes.autoencoder_kl.AutoencoderKLVAEConfig","has_param_spec_type":false,"metaclass_type":null,"metadata":{"dataclass":{"attributes":[{"alias":null,"column":4,"has_default":true,"is_in_init":true,"is_init_var":false,"is_neither_frozen_nor_nonfrozen":false,"kw_only":false,"line":39,"name":"arch_config","type":{".class":"AnyType","missing_import_name":"FastVideo.fastvideo.configs.models.vaes.autoencoder_kl.VAEArchConfig","source_any":null,"type_of_any":3}}],"frozen":false},"dataclass_tag":{}},"module_name":"FastVideo.fastvideo.configs.models.vaes.autoencoder_kl","mro":["FastVideo.fastvideo.configs.models.vaes.autoencoder_kl.AutoencoderKLVAEConfig","builtins.object"],"names":{".class":"SymbolTable","__dataclass_fields__":{".class":"SymbolTableNode","kind":"Mdef","node":{".class":"Var","flags":["is_classvar","is_ready"],"fullname":"FastVideo.fastvideo.configs.models.vaes.autoencoder_kl.AutoencoderKLVAEConfig.__dataclass_fields__","name":"__dataclass_fields__","type":{".class":"Instance","args":["builtins.str",{".class":"Instance","args":[{".class":"AnyType","missing_import_name":null,"source_any":null,"type_of_any":2}],"extra_attrs":null,"type_ref":"dataclasses.Field"}],"extra_attrs":null,"type_ref":"builtins.dict"}},"plugin_generated":true},"__init__":{".class":"SymbolTableNode","kind":"Mdef","node":{".class":"FuncDef","abstract_status":0,"arg_kinds":[0,2,1,4],"arg_names":["self","generated_args","arch_config","generated_kwargs"],"dataclass_transform_spec":null,"deprecated":null,"flags":[],"fullname":"FastVideo.fastvideo.configs.models.vaes.autoencoder_kl.AutoencoderKLVAEConfig.__init__","name":"__init__","type":{".class":"CallableType","arg_kinds":[0,2,1,4],"arg_names":["self","generated_args","arch_config","generated_kwargs"],"arg_types":["FastVideo.fastvideo.configs.models.vaes.autoencoder_kl.AutoencoderKLVAEConfig",{".class":"AnyType","missing_import_name":null,"source_any":null,"type_of_any":2},{".class":"AnyType","missing_import_name":"FastVideo.fastvideo.configs.models.vaes.autoencoder_kl.VAEArchConfig","source_any":null,"type_of_any":3},{".class":"AnyType","missing_import_name":null,"source_any":null,"type_of_any":2}],"bound_args":[],"def_extras":{},"fallback":"builtins.function","from_concatenate":false,"implicit":false,"imprecise_arg_kinds":false,"is_ellipsis_args":false,"name":"__init__ of AutoencoderKLVAEConfig","ret_type":{".class":"NoneType"},"type_guard":null,"type_is":null,"unpack_kwargs":false,"variables":[]}},"plugin_generated":true},"__match_args__":{".class":"SymbolTableNode","kind":"Mdef","node":{".class":"Var","flags":["is_ready","allow_incompatible_override"],"fullname":"FastVideo.fastvideo.configs.models.vaes.autoencoder_kl.AutoencoderKLVAEConfig.__match_args__","name":"__match_args__","type":{".class":"TupleType","implicit":false,"items":[{".class":"LiteralType","fallback":"builtins.str","value":"arch_config"}],"partial_fallback":{".class":"Instance","args":[{".class":"AnyType","missing_import_name":null,"source_any":null,"type_of_any":6}],"extra_attrs":null,"type_ref":"builtins.tuple"}}},"plugin_generated":true},"__mypy-replace":{".class":"SymbolTableNode","kind":"Mdef","node":{".class":"Decorator","func":{".class":"FuncDef","abstract_status":0,"arg_kinds":[5],"arg_names":["arch_config"],"dataclass_transform_spec":null,"deprecated":null,"flags":["is_static","is_decorated"],"fullname":"FastVideo.fastvideo.configs.models.vaes.autoencoder_kl.AutoencoderKLVAEConfig.__mypy-replace","name":"__mypy-replace","type":{".class":"CallableType","arg_kinds":[5],"arg_names":["arch_config"],"arg_types":[{".class":"AnyType","missing_import_name":"FastVideo.fastvideo.configs.models.vaes.autoencoder_kl.VAEArchConfig","source_any":null,"type_of_any":3}],"bound_args":[],"def_extras":{},"fallback":"builtins.function","from_concatenate":false,"implicit":false,"imprecise_arg_kinds":false,"is_ellipsis_args":false,"name":"__mypy-replace of AutoencoderKLVAEConfig","ret_type":{".class":"NoneType"},"type_guard":null,"type_is":null,"unpack_kwargs":false,"variables":[]}},"is_overload":false,"var":{".class":"Var","flags":["is_staticmethod","is_ready"],"fullname":"FastVideo.fastvideo.configs.models.vaes.autoencoder_kl.AutoencoderKLVAEConfig.__mypy-replace","name":"__mypy-replace","type":{".class":"CallableType","arg_kinds":[5],"arg_names":["arch_config"],"arg_types":[{".class":"AnyType","missing_import_name":"FastVideo.fastvideo.configs.models.vaes.autoencoder_kl.VAEArchConfig","source_any":null,"type_of_any":3}],"bound_args":[],"def_extras":{},"fallback":"builtins.function","from_concatenate":false,"implicit":false,"imprecise_arg_kinds":false,"is_ellipsis_args":false,"name":"__mypy-replace of AutoencoderKLVAEConfig","ret_type":{".class":"NoneType"},"type_guard":null,"type_is":null,"unpack_kwargs":false,"variables":[]}}},"plugin_generated":true},"arch_config":{".class":"SymbolTableNode","kind":"Mdef","node":{".class":"Var","flags":["is_initialized_in_class","is_ready","has_explicit_value"],"fullname":"FastVideo.fastvideo.configs.models.vaes.autoencoder_kl.AutoencoderKLVAEConfig.arch_config","name":"arch_config","type":{".class":"AnyType","missing_import_name":"FastVideo.fastvideo.configs.models.vaes.autoencoder_kl.VAEArchConfig","source_any":null,"type_of_any":3}}}},"self_type":{".class":"TypeVarType","default":{".class":"AnyType","missing_import_name":null,"source_any":null,"type_of_any":4},"fullname":"FastVideo.fastvideo.configs.models.vaes.autoencoder_kl.AutoencoderKLVAEConfig.Self","id":0,"name":"Self","namespace":"","upper_bound":"FastVideo.fastvideo.configs.models.vaes.autoencoder_kl.AutoencoderKLVAEConfig","values":[],"variance":0},"slots":null,"tuple_type":null,"type_vars":[],"typeddict_type":null}},"VAEArchConfig":{".class":"SymbolTableNode","kind":"Gdef","node":{".class":"Var","flags":["is_suppressed_import","is_ready","is_inferred"],"fullname":"FastVideo.fastvideo.configs.models.vaes.autoencoder_kl.VAEArchConfig","name":"VAEArchConfig","type":{".class":"AnyType","missing_import_name":"FastVideo.fastvideo.configs.models.vaes.autoencoder_kl.VAEArchConfig","source_any":null,"type_of_any":3}}},"VAEConfig":{".class":"SymbolTableNode","kind":"Gdef","node":{".class":"Var","flags":["is_suppressed_import","is_ready","is_inferred"],"fullname":"FastVideo.fastvideo.configs.models.vaes.autoencoder_kl.VAEConfig","name":"VAEConfig","type":{".class":"AnyType","missing_import_name":"FastVideo.fastvideo.configs.models.vaes.autoencoder_kl.VAEConfig","source_any":null,"type_of_any":3}}},"__annotations__":{".class":"SymbolTableNode","kind":"Gdef","node":{".class":"Var","flags":["is_ready"],"fullname":"FastVideo.fastvideo.configs.models.vaes.autoencoder_kl.__annotations__","name":"__annotations__","type":{".class":"Instance","args":["builtins.str",{".class":"AnyType","missing_import_name":null,"source_any":null,"type_of_any":6}],"extra_attrs":null,"type_ref":"builtins.dict"}}},"__doc__":{".class":"SymbolTableNode","kind":"Gdef","node":{".class":"Var","flags":["is_ready"],"fullname":"FastVideo.fastvideo.configs.models.vaes.autoencoder_kl.__doc__","name":"__doc__","type":"builtins.str"}},"__file__":{".class":"SymbolTableNode","kind":"Gdef","node":{".class":"Var","flags":["is_ready"],"fullname":"FastVideo.fastvideo.configs.models.vaes.autoencoder_kl.__file__","name":"__file__","type":"builtins.str"}},"__name__":{".class":"SymbolTableNode","kind":"Gdef","node":{".class":"Var","flags":["is_ready"],"fullname":"FastVideo.fastvideo.configs.models.vaes.autoencoder_kl.__name__","name":"__name__","type":"builtins.str"}},"__package__":{".class":"SymbolTableNode","kind":"Gdef","node":{".class":"Var","flags":["is_ready"],"fullname":"FastVideo.fastvideo.configs.models.vaes.autoencoder_kl.__package__","name":"__package__","type":"builtins.str"}},"__spec__":{".class":"SymbolTableNode","kind":"Gdef","node":{".class":"Var","flags":["is_ready"],"fullname":"FastVideo.fastvideo.configs.models.vaes.autoencoder_kl.__spec__","name":"__spec__","type":"_frozen_importlib.ModuleSpec"}},"dataclass":{".class":"SymbolTableNode","cross_ref":"dataclasses.dataclass","kind":"Gdef"},"field":{".class":"SymbolTableNode","cross_ref":"dataclasses.field","kind":"Gdef"},"torch":{".class":"SymbolTableNode","kind":"Gdef","node":{".class":"Var","flags":["is_suppressed_import","is_ready","is_inferred"],"fullname":"FastVideo.fastvideo.configs.models.vaes.autoencoder_kl.torch","name":"torch","type":{".class":"AnyType","missing_import_name":"FastVideo.fastvideo.configs.models.vaes.autoencoder_kl.torch","source_any":null,"type_of_any":3}}}},"path":"fastvideo/configs/models/vaes/autoencoder_kl.py"}